{
  "post_id": 2643,
  "updated_at": "2026-03-11T20:32:58.260541+00:00",
  "comments": [
    {
      "id": 838496,
      "author": "Oleg",
      "text": "Не могу сказать. Иногда захожу блюзовые лики в одной группе посмотреть, а так - помойка.",
      "date": "2025-07-09T17:31:23+00:00"
    },
    {
      "id": 838495,
      "author": "Елена Учет, налоги, кадры",
      "text": "Сильно вдумчивого. Ничего не грузится",
      "date": "2025-07-09T17:29:51+00:00"
    },
    {
      "id": 838493,
      "author": "Oleg",
      "text": "ВК, кажется, не позиционируют себя, как площадка для вдумчивого чтения. Так что не удивительно наблюдать побег многих авторов оттуда",
      "date": "2025-07-09T17:26:13+00:00"
    },
    {
      "id": 838492,
      "author": "Roman Bevzenko",
      "text": "Нет, забросил",
      "date": "2025-07-09T17:17:52+00:00"
    },
    {
      "id": 838486,
      "author": "Denis Sebrowski",
      "text": "Роман Сергеевич, VK больше не ведете блог? Как-то меньше активности там стало 😏",
      "date": "2025-07-09T16:02:37+00:00"
    }
  ]
}