{
  "post_id": 2792,
  "updated_at": "2026-03-11T20:32:58.215364+00:00",
  "comments": [
    {
      "id": 858996,
      "author": "Сергей",
      "text": "Такие дела в пользу истца (якобы обманутого мошенниками продавца) были и до неё. Ее дело, видимо, усилило тренд на такие решения, хотя иногда суды и выносили решения в пользу ответчиков.",
      "date": "2025-10-19T13:39:40+00:00"
    },
    {
      "id": 858994,
      "author": "Андрей Николаев",
      "text": "Сегодня был большой репортаж по России , про это дело тоже говорили.  А вот про народную артистку , которая запустила этот вирусный процесс, не сказали.",
      "date": "2025-10-19T13:29:07+00:00"
    },
    {
      "id": 858957,
      "author": "Сергей",
      "text": "А знаете номер дела, где продавец сходил в а полицию перед сделкой?",
      "date": "2025-10-19T08:40:49+00:00"
    },
    {
      "id": 858592,
      "author": "Thomas Muller",
      "text": "После дела Ивановского завода не хочется ничего этого читать, слушать \"свежие\" ветра, к сожалению.\nНа мой взгляд, ничего не изменилось, стало хуже. P.s. понимаю всю иронию Романа Сергеевича про эти ветра.",
      "date": "2025-10-17T10:05:22+00:00"
    },
    {
      "id": 858591,
      "author": "Djuffin",
      "text": "Росреестр регистрирует всё что угодно. Поэтому доверия ЕГРН и нет.",
      "date": "2025-10-17T10:03:07+00:00"
    },
    {
      "id": 858582,
      "author": "Robert Maksotckii",
      "text": "Немножко не в тему: но напомню, что даже иски госучреждений (конкретно - медучреждения) к гражданину об опровержении сведений, «подведомственны» именно арбитражным судам)",
      "date": "2025-10-17T09:15:24+00:00"
    },
    {
      "id": 858580,
      "author": "Artem Barinov",
      "text": "Ну это не простой спор. Тут стандарт субъективной добросовестности снизили до простого обращения к реестру и полностью перевернули игру",
      "date": "2025-10-17T09:14:11+00:00"
    },
    {
      "id": 858579,
      "author": "Oleg",
      "text": "странная логика суда. ИП - это статус человека. Но все ещё человека.",
      "date": "2025-10-17T09:13:45+00:00"
    },
    {
      "id": 858577,
      "author": "Vagan Minasian",
      "text": "Вы думаете у нас ИП был в АСГМ?) Нет, мы умеем и иски граждан в АСГМ подавать.",
      "date": "2025-10-17T09:11:58+00:00"
    },
    {
      "id": 858576,
      "author": "Sergey Podyapolsky",
      "text": "Вроде бы была правовая позиция, что индивидуальный предприниматель это не человек, а правовая конструкция. Поэтому ИП не может испытывать эмоций и нравственных страданий, а значит, ему не нужно компенсировать моральный вред.",
      "date": "2025-10-17T09:10:34+00:00"
    },
    {
      "id": 858572,
      "author": "Vagan Minasian",
      "text": "Откройте карточку арбитражных дел, выберите ДГИ в качестве истца посмотрите последние дел 10 хотя-бы. Почти все дела по сносу самовольных. Из 10 дел 7-8 отказные с взысканием с ДГИ судебных расходов за экспертизу. Это их не останавливает. Денег в бюджете видимо предостаточно. Не такие уж они и непобедимые в простых спорах. А вот где замешаны крупные стройки, большие деньги у них есть есть какие-то подвязки. У нас например недавно по одной крупной стройке судья вела все по процессу, истребовала документы, не спешила, потом что-то резко произошло, судью заменили, все запросы отозвали и отказали в иске. Судья принявший исковое заявление к производству при этом сидела в кабинете с опущенными глазами.",
      "date": "2025-10-17T08:56:01+00:00"
    },
    {
      "id": 858566,
      "author": "Artem Barinov",
      "text": "Да еще и не в пользу Москвы решили, чудеса какие",
      "date": "2025-10-17T08:51:35+00:00"
    },
    {
      "id": 858563,
      "author": "Vagan Minasian",
      "text": "Я лично плюнул, даже в лицо все высказал. Ничего не потерял, только приобрел. Да я бы даже не сказал, что во время работы приходилось что-то такое исполнять. На госслужбе вполне можно поставить себя так, что тебе даже предлагать не будут такие дела вести. Этим и занимался. Разумеется рост по должностям будет закрыт после какого-то момента. Но тут ты выбираешь, оставаться частью этого мясорубки или нет. И вот что интересно, те у кого есть достаточно мозгов и самоуважения иногда выбирают уйти и реализовывать себя в коммерции, но те кто не уверен в себе и лучше других знает о себе, они остаются. Они остаются надолго. Проф деформация приводит к правовым позициям, которые я слушал вчера в АСГМ - \"у граждан нет прав, они не могут быть нарушены\".",
      "date": "2025-10-17T08:49:25+00:00"
    },
    {
      "id": 858561,
      "author": "Максим",
      "text": "Думаю про себя лет в 25-30. Ни семьи, ни обязательств. И вот при таких условиях, что прикольней, держаться за достойную (нет) зарплату или с удовольствием и пафосом плюнуть в лицо начальнику, раздающему подобные задания?",
      "date": "2025-10-17T08:44:51+00:00"
    },
    {
      "id": 858555,
      "author": "Vagan Minasian",
      "text": "Наверное не так, Роман Сергеевич. Не Москва, а ДГИ г. Москвы, в котором работают одни из лучших юристов в стране (нет). Перед которыми ставят буквально задачу по отъему у москвичей как можно большего количества имущества. С тем же успехом можем говорить, что это не прокуратура иски подает, а Российская Федерация.",
      "date": "2025-10-17T08:39:08+00:00"
    },
    {
      "id": 858548,
      "author": "Виталий",
      "text": "Как видно из обсуждаемого дела - в 3-х инстанциях у г.Москвы это вполне получилось.\nЕсли под \"нет сейчас\" Вы имеете ввиду - нет записи в реестре=нет права собственности (принцип внесения) - имеет смысл обратиться к п.2 ст 8.1 ГК на предмет исключений из принципа внесения.",
      "date": "2025-10-17T08:17:54+00:00"
    },
    {
      "id": 858541,
      "author": "Adm",
      "text": "Для \"Не владеющего собственника (которого нет в егрн)\" основной задачей будет доказать правовые основания своего права собственности (еще раз- которого нет сейчас и не было никогда в егрн) + конечно же Ответчик заявит СИД (что преодолеть будет сложно)",
      "date": "2025-10-17T08:00:22+00:00"
    },
    {
      "id": 858540,
      "author": "Роман",
      "text": "дело дубовца в помощь)",
      "date": "2025-10-17T07:57:16+00:00"
    },
    {
      "id": 858539,
      "author": "Виталий",
      "text": "Виндикационный иск возможен не владеющего собственника (в данном случае г. Москва - не в реестре) к владеющему НЕ собственнику (гражданка - ответчик, в реестре)",
      "date": "2025-10-17T07:49:13+00:00"
    },
    {
      "id": 858538,
      "author": "Роман",
      "text": "конечно, нет\n\nзачем мне вообще с виндикацией идти (да ее и быть не может, если есть договор)? \n\nпришел, сменил ключи, замок, ваши вещи описал и на хранение передал \n\nв суд пойду с иском о взыскании убытков в размере платы за время, когда вы там были сверх срока договора + расходов на хранение (если только не удержал вещи в счет аренды)\n\nисключение с жилым помещением, так как там выселять именно через суд нужно",
      "date": "2025-10-17T07:49:12+00:00"
    },
    {
      "id": 858535,
      "author": "Роман",
      "text": "виндикация возможна, если я собственник, и об этом идет спор, собственник я или нет\n\nпо забору: да, чтобы компенсировать затраты на снос и возведение нового",
      "date": "2025-10-17T07:43:07+00:00"
    },
    {
      "id": 858534,
      "author": "Виталий",
      "text": "Если на Вас запись в реестре, а по истечении 3х лет по окончании нашего договора аренды я не вернул Вам помещение - с каким иском пойдёте?\nНе с виндикацией-ли?",
      "date": "2025-10-17T07:42:28+00:00"
    },
    {
      "id": 858531,
      "author": "სერხიო",
      "text": "Кому компенсировать",
      "date": "2025-10-17T07:34:53+00:00"
    },
    {
      "id": 858528,
      "author": "Роман",
      "text": "владение недвижимостью передается внесением записи в реестр \n\nмне не нужно с записию в реестр идти с виндикацией (виндикация защищает собственность, а не владение)\n\nмне достаточно сменить замок, снести забор и тп",
      "date": "2025-10-17T07:29:52+00:00"
    },
    {
      "id": 858524,
      "author": "Антон",
      "text": "💯",
      "date": "2025-10-17T07:28:00+00:00"
    },
    {
      "id": 858523,
      "author": "Виталий",
      "text": "Владение, передается затем, что если Вы владеющий собственник (условно говоря с ключами) - вы идёте с иском по 304 ГК и срока давности по нему нет.\nА если у Вас нет владения - то 301, 302 с ИД в 3 года.",
      "date": "2025-10-17T07:27:30+00:00"
    },
    {
      "id": 858521,
      "author": "Z V",
      "text": "Ну, в реестре то может быть и дядя Вася, абсолютно левый. Мало ли, что туда тетка регистратор по глупости или невнимательности внесёт. Мы же юристы, должны искать объективную  истину, а не доверять тетке регистратору. Или не так все? Чёт я запутался😁",
      "date": "2025-10-17T07:24:17+00:00"
    },
    {
      "id": 858520,
      "author": "Роман",
      "text": "понятия не имею, бред потому что\n\nа точнее, 556 не менялась со времени принятия ГК, в то время как общую часть изменяли несколько раз, в том числе внесением ст. 8.1 ГК",
      "date": "2025-10-17T07:22:51+00:00"
    },
    {
      "id": 858519,
      "author": "Андрей",
      "text": "А ведь эта проблема только набирает обороты. \n\nВ социальных сетях мелькает достаточно историй о том, как покупатели остаются без квартир и денег под этим самым предлогом, что продавец действовал под давлением мошенников. \n\nВ одной истории покупатель даже придумал сходить вместе с продавцом в полицию, чтобы тот подтвердил, что не находится под давлением. Но и это не уберегло. \n\nИз этого всего теперь две насущные проблемы следует. Рынок вторичной недвижимости становится непривлекательным. \nНу и порождает новый вид мошенников внутри страны.",
      "date": "2025-10-17T07:22:03+00:00"
    },
    {
      "id": 858518,
      "author": "Виталий",
      "text": "А зачем тогда передаточный акт (п.1 ст 556 ГК) подписывается?",
      "date": "2025-10-17T07:18:32+00:00"
    },
    {
      "id": 858516,
      "author": "Роман",
      "text": "потому что владение для недвижимости — это запись в реестре",
      "date": "2025-10-17T07:14:38+00:00"
    },
    {
      "id": 858515,
      "author": "Виталий",
      "text": "Вы про то - почему Москва не собственник?\nВладение - у ответчика, как я понимаю.",
      "date": "2025-10-17T07:13:32+00:00"
    },
    {
      "id": 858514,
      "author": "Z V",
      "text": "Падажжи, падажжи. У нас же же выморочное имущество наследуется на общих основаниях. Для выморочного имущества не нужно принятие наследства (п.1 си.1152) Отказ не допускается от такого имущества публичного субъекта (п.1 что.1157). Так какого лешего Москва не владелец?🧐",
      "date": "2025-10-17T07:12:26+00:00"
    },
    {
      "id": 858513,
      "author": "roman t",
      "text": "Понятно, спасибо",
      "date": "2025-10-17T07:03:49+00:00"
    },
    {
      "id": 858511,
      "author": "Z V",
      "text": "Падажжи, а Москва же стала владельцем законным. Квартира выморочная. А как же тогда п.1 ст.302?",
      "date": "2025-10-17T07:02:49+00:00"
    },
    {
      "id": 858509,
      "author": "Roman Bevzenko",
      "text": "Как говорят англичане, hard cases make bad law",
      "date": "2025-10-17T06:56:58+00:00"
    },
    {
      "id": 858508,
      "author": "Константин Lawyer",
      "text": "Очень хорошо👍! Спасибо🥃 но даже если покупатель ознакомился или нет со всеми предыдущими правоустанавливающими документами, не оспоренными в установленном порядке, какое это имеет значение, ежели все эти документы не единожды (дважды или более) проверялись специально уполномоченным государственным органом - Росреестром?! В данном случае добросовестность покупателя должна подразумеваться. Но рука советника мэра егоровой продолжает чувствоваться в повседневной реальности московского правосудия. А от дел по выморочным квартирам московские судьи шарахаются как чорт от ладана с августа 2005, когда савелюку, ивченко и мишиной вс рф \"сунул\" 37 лет на троих. \nФабула дела потрясающая: выморочное имущество; нотариус федорченко; завещание 2010 года, до электронного реестра; проживание в местности без электричества; 10 лет нет связи с наследодателем; цена 4 млн = 1/3 рынка и тд и тп. Классика жанра, мечта \"адвоката раевского\" - организатора по делу трёх судей🤣",
      "date": "2025-10-17T06:56:57+00:00"
    },
    {
      "id": 858507,
      "author": "Roman",
      "text": "Отлично! Как бы эту разумную практику еще синхронизировать с делами об оспаривании сделок с недвижимостью \"а ля Долина\"",
      "date": "2025-10-17T06:56:22+00:00"
    },
    {
      "id": 858506,
      "author": "Роман",
      "text": "у нас регистрационная система так называемая негативная. под ней должно быть действительное основание. если его нет, регистрация не породит права\n\nвот и пытаются основание рушить\n\nно регистратор как бы должен действительность этого основания проверять, поэтому покупатель заново эту работу делать не должен",
      "date": "2025-10-17T06:53:05+00:00"
    },
    {
      "id": 858505,
      "author": "Anton",
      "text": "👍",
      "date": "2025-10-17T06:50:37+00:00"
    },
    {
      "id": 858504,
      "author": "roman t",
      "text": "Я профан, скажу сразу, но как истребование судом удовлетворяется, если право возникает с регистрацией?",
      "date": "2025-10-17T06:45:31+00:00"
    },
    {
      "id": 858501,
      "author": "Максим Шедогубов",
      "text": "Отличная новость! Спасибо, Роман! Если бы ещё не закрытый в угоду понятно кого реестр, было бы совсем замечательно",
      "date": "2025-10-17T06:43:10+00:00"
    }
  ]
}