{
  "post_id": 2813,
  "updated_at": "2026-03-11T20:32:58.210314+00:00",
  "comments": [
    {
      "id": 860195,
      "author": "Александр",
      "text": "Спасибо🔥🙏🏻",
      "date": "2025-10-25T10:46:02+00:00"
    },
    {
      "id": 860180,
      "author": "Diakov Kirill",
      "text": "Это было эпично)",
      "date": "2025-10-25T09:09:55+00:00"
    },
    {
      "id": 860171,
      "author": "Дмитрий Большаков",
      "text": "Раз уж начинается гонка юридических роботов, то мы решили дать юристам инструмент для их быстрого и легкого создания без программирования. Кто знает, может сам Роман или кто-то из юристов сделает на нашей платформе робота, который победит в следующем раунде :)",
      "date": "2025-10-25T08:35:19+00:00"
    },
    {
      "id": 860170,
      "author": "Roman Bevzenko",
      "text": "теперь должно работать",
      "date": "2025-10-25T08:32:59+00:00"
    },
    {
      "id": 860169,
      "author": "Roman Bevzenko",
      "text": "О, не обратил внимание, что видео еще обрабатывается. Чуть позже будет доступно",
      "date": "2025-10-25T08:27:50+00:00"
    },
    {
      "id": 860168,
      "author": "Vurse",
      "text": "😟🤨",
      "date": "2025-10-25T08:27:07+00:00"
    }
  ]
}