{
  "post_id": 2825,
  "updated_at": "2026-03-11T20:32:58.204827+00:00",
  "comments": [
    {
      "id": 866057,
      "author": "Александр Смолин",
      "text": "... а чиновник делая запись о переходе собственности несобственнику фактически действовал не по инструкции (по инструкции только о переходе права собственности  собственнику можно запись делать), а значит он действовал не в рамках своего статуса чиновника, а в личном качестве, а значит за него государство отвечать не должно🤗",
      "date": "2025-11-20T14:36:16+00:00"
    },
    {
      "id": 863925,
      "author": "Valery Vladimirets",
      "text": "Записать принудительно умных в адвокаты, чтоб не повадно :))))",
      "date": "2025-11-11T08:02:51+00:00"
    },
    {
      "id": 863549,
      "author": "Андрей Салов",
      "text": "Если собственника обманули и далее продали его жилое помещение добросовестному приобретателю, у которого затем собственник виндицировал вещь, то ст.68.1 не применима? Действительно такая судебная практика? \nИз содержания этой нормы не следует, что она сводится к ошибке регистратора.",
      "date": "2025-11-09T07:27:07+00:00"
    },
    {
      "id": 863235,
      "author": "A.",
      "text": "Полностью, с Вами согласен.  И судебная практика уже есть по таким искам.",
      "date": "2025-11-07T13:41:02+00:00"
    },
    {
      "id": 863043,
      "author": "Денис",
      "text": "Сам создаю вопросы, сам их решаю",
      "date": "2025-11-07T07:40:03+00:00"
    },
    {
      "id": 863003,
      "author": "Andrey Chevychelov",
      "text": "Лучший маркетинговый слоган должен быть: \"Решаю любые вопросы\"",
      "date": "2025-11-07T05:50:15+00:00"
    },
    {
      "id": 862955,
      "author": "Вадим О́бвинцев",
      "text": "Этот пост или статья адвоката ориентировалась на определенную целевую аудиторию как маркетинговая приманка, а не на юристов. Этику оставляем за скобками.",
      "date": "2025-11-06T21:00:04+00:00"
    },
    {
      "id": 862909,
      "author": "Ирина",
      "text": "Потому что \"денежные средства за квартиру получены злоумышленниками\". Сильный аргумент, пуленепробиваемый практически:) \n\"подлежат установлению в рамках производства по уголовному делу\", к которому покупатель не имеет отношения.\nЧто ж, меня всё ещё можно удивить. Когда суд определился с результатом, его никакой закон не остановит",
      "date": "2025-11-06T17:22:27+00:00"
    },
    {
      "id": 862878,
      "author": "Евгений",
      "text": "для него глупость неочевидна, специально глупые советы нормальный человек не будет, тем более публично. Глупость не в советах, глупость в непонимании границ своей компетенции.",
      "date": "2025-11-06T16:40:16+00:00"
    },
    {
      "id": 862873,
      "author": "Alex",
      "text": "Полностью согласен. Прежде чем что-либо говорить, надо тщательно подумать.",
      "date": "2025-11-06T16:36:28+00:00"
    },
    {
      "id": 862869,
      "author": "Евгений",
      "text": "то же самое можно сказать про врачей, сантехников, автомехаников и так далее. Профессионалов днем с огнем не найдешь во всех сферах.",
      "date": "2025-11-06T16:34:13+00:00"
    },
    {
      "id": 862866,
      "author": "Mirko",
      "text": "А как сами порекомендуете заключать сделки с \"пенсионерами-оперативниками\"?\nПроблема-то серьезная. В новостях все новые и новые случаи показывают. Правда с реституцией и последующим банкротством должника.",
      "date": "2025-11-06T16:22:48+00:00"
    },
    {
      "id": 862855,
      "author": "Денис",
      "text": "Когда у общества нет цветовой дифференциации штанов, то нет цели! А когда нет цели...",
      "date": "2025-11-06T15:36:55+00:00"
    },
    {
      "id": 862854,
      "author": "Liliya",
      "text": "Люди это божьи твари, которым закон изначально не писан. Не помогла даже трансформация принятых ранее норм из религии в социум. Для меня адвокаты и юристы это те же самые двуногие, которые в одном котелке. Разницы не вижу, грязь в человеке статусом не прикрыть.",
      "date": "2025-11-06T15:36:50+00:00"
    },
    {
      "id": 862852,
      "author": "Максим Шедогубов",
      "text": "Безусловно. Вот только юристы не делают из своей профессии сакральную и не называют адвокатов всякими детсадовскими словечками.",
      "date": "2025-11-06T15:28:57+00:00"
    },
    {
      "id": 862849,
      "author": "Shaikhutdinov Dinar",
      "text": "По мне, так ст. 68.1 Закона о регистрации не ставит под условие возможность получения компенсации лишь из-за  ошибки регистратора. Как раз таки в случае ошибки регистратора, убытки возмещаются по ч.2 ст. 66 указанного закона.",
      "date": "2025-11-06T15:07:08+00:00"
    },
    {
      "id": 862830,
      "author": "Максим Шедогубов",
      "text": "Чего это Вы меня так в звании понизили? С утра только демоном был 😈",
      "date": "2025-11-06T14:20:51+00:00"
    },
    {
      "id": 862824,
      "author": "Vagan Minasian",
      "text": "В малой беде)) \"Всегда найдется рыба покрупнее\".",
      "date": "2025-11-06T14:10:11+00:00"
    },
    {
      "id": 862823,
      "author": "Liliya",
      "text": "Это уже свойство человеческой натуры) Видеть свет и не замечать тьму. Кто без забрала в виде собственной исключительности-почестнее будет.",
      "date": "2025-11-06T14:09:46+00:00"
    },
    {
      "id": 862821,
      "author": "Александр Валявский",
      "text": "Отечественное право окажется в большой беде🤣 А сейчас где оно?!!",
      "date": "2025-11-06T14:08:43+00:00"
    },
    {
      "id": 862810,
      "author": "Vagan Minasian",
      "text": "Во-первых рад что полностью сошелся в правовом анализе судебных актов по этому ужасному делу. Во-вторых касаемо адвокатов, я бы вот что хотел отметить, у меня есть две теории, обе внушают страх за будущее. Первая теория о том, что у нас вообще нет приличных адвокатов в стране за редким исключением. Веду свою статистику, вижу как в праве разбирается 1 адвокат из 10, которые встречаются по дороге. Вторая теория, они все примерно понимают право, но их интерес направлен не на защиту своего клиента, а на зароботок. Тот самый анекдот про кормящее дело. Вот вы даже пример привели, я не понимаю, как можно такое написать, но если взять в расчет, что за такие иски берут деньги и ходят аж до кассации, то можно прийти к выводу, что адвокат просто ищет клиентов. Так что отечественно право окажется в большой беде если АМ примут.",
      "date": "2025-11-06T13:50:48+00:00"
    },
    {
      "id": 862809,
      "author": "Liliya",
      "text": "Черти есть в любой профессии. Юристы не исключение.",
      "date": "2025-11-06T13:45:10+00:00"
    },
    {
      "id": 862808,
      "author": "A. B.",
      "text": "👍",
      "date": "2025-11-06T13:44:33+00:00"
    },
    {
      "id": 862807,
      "author": "Максим Шедогубов",
      "text": "Нет. Не лучше. Тот же треш, угар и содомия, как и везде.",
      "date": "2025-11-06T13:43:33+00:00"
    },
    {
      "id": 862789,
      "author": "Мария Гиря | Семейный юрист",
      "text": "Вот я то же самое сейчас думаю про дело Долиной. Через сми формируется восприятие людей о том, что можно так просто прийти в суд и сказать: извините, я ошибся. Ах, ошибся? ну тогда да, уничтожим сделку. Ну как такое может быть?? Мне уже позвонил клиент с вопросом, можно ли обнулить дарение, я хотел таким образом наладить отношения с дочерью, но не вышло 🤯",
      "date": "2025-11-06T13:12:55+00:00"
    },
    {
      "id": 862768,
      "author": "Andrey Chevychelov",
      "text": "Ну, полноте, сударь! Присяжный повѣренный  худаго не посовѣтуетъ",
      "date": "2025-11-06T12:42:03+00:00"
    },
    {
      "id": 862753,
      "author": "Danil",
      "text": "Полностью согласен. Сколько раз сталкивался в процессе с адвокатами, большинство это тихий ужас. В Москве, думаю, с этим получше обстоят дела",
      "date": "2025-11-06T11:56:50+00:00"
    },
    {
      "id": 862740,
      "author": "Serg Mo",
      "text": "Ещё бы кто знал как и чем измерять качество и кто это должен делать.",
      "date": "2025-11-06T11:30:50+00:00"
    },
    {
      "id": 862736,
      "author": "A.",
      "text": "Роман Сергеевич, добрый день! \nНе совсем согласен с Вами, возможно буду не прав. Но для себя хочется разобраться в вопросе.\nДа, действительно \n«Нормы ст. 68.1 являются компенсационным механизмом, рассчитанным на поддержание доверия к реестру недвижимости» с Вами согласен. \n\n«Они предполагают, что если регистратор ошибся и внес запись о праве собственности за лицом, которое в действительности таковым не являлось, то тот, кто положился на запись и совершил сделку с неуправомоченным лицом, не должен пострадать от ошибки регистратора», здесь не соглашусь. \n\nПолагаю, что речь не идет только об ошибке регистратора и внесения записи. Речь идет о том, что если Покупатель полагался на данные государственного реестра ЕГРН (соответственно он будет являться добросовестным) он имеет право на компенсацию. \n\nВедь бывают случаи, когда есть цепочки сделок, и сделки признают спустя существенный отрезок времени после приобретения последним покупателем недействительными.",
      "date": "2025-11-06T11:21:28+00:00"
    },
    {
      "id": 862735,
      "author": "Nina",
      "text": "А если с участием суда присяжных, считается?",
      "date": "2025-11-06T11:17:06+00:00"
    },
    {
      "id": 862725,
      "author": "Sorgenfrei",
      "text": "Кодекс профессиональной этики распространяется на  адвокатов, а не претендующих на приобретение статуса. Просто по закону. Когда очередной ужасный мент судимый по 159, 285, 290 УК или ещё какой-то странный персонаж через n лет всплывает в статусе адвоката, то это не проблема адвокатуры. Есть список формальных требований предъявляемых к кандидату и они перечислены в законе. Вы же сами откроете ящик Пандоры допуская будто бы можно отказывать в сдаче экзамена по субъективным мотивам. Иначе будет как с судьями, когда сдавать может любой, а вот получить назначение уже вопрос субъективных критериев отбора",
      "date": "2025-11-06T10:58:56+00:00"
    },
    {
      "id": 862724,
      "author": "Максим Латкин",
      "text": "Он же вроде должен подлежать ответственности за обещание заведомо неправового результата ?\nИли это касается только конкретного клиента?\nВ целом, конечно было бы очень хорошо, если бы в адвокатуре навели такой порядок, который не позволял бы кому угодно получать адвокатский статус, с периодической и регулярной переаттестацией под угрозой лишения статуса при провале.\nТогда хотелось бы получать статус адвоката.\n\nИ получается странно, адепты реформы хотят защитить потребителя от низкого качества юридических услуг, но получается из пустого в порожнее.",
      "date": "2025-11-06T10:57:08+00:00"
    },
    {
      "id": 862721,
      "author": "Максим Шедогубов",
      "text": "То есть святая для каждого адвоката книга: Кодекс адвокатской этики, это так, посмеяться написали? И люди, явно не проходящие этот фильтр, но получающие статус адвоката снова и снова — норма? Никто бы адвокатов не трогал, даже на вот этот смешной пафос плевать, если бы палата не пыталась заигрывать с монополией. Я с огромным уважением отношусь к самому институту адвокатуры, являюсь сторонником профессионального процесса, но российская адвокатура представляет собой печальное зрелище. Несмотря на наличие некоторого числа блестящих представителей профессии. Работу и Добровинского, и Пашаева вся страна наблюдала практически в прямом эфире. Жалкое зрелище даже для не профессионала",
      "date": "2025-11-06T10:52:27+00:00"
    },
    {
      "id": 862718,
      "author": "Sorgenfrei",
      "text": "То есть это Ваше мнение? Не думаю, что это имеет роль при оценке работы Добровинского или даже Пашаева. Вот решение палат - имеет. Как и решение клиентов обращаться к определённым специалистам. Повторно приобрести статус закон не запрещает. В этой связи претензия не совсем ясна: палаты должны незаконно препятствовать повторной сдаче экзамена? Почему тогда только им, а не кому-то ещё по столь же субъективным критериям? Тому же Пашаеву статус прекращали несколько раз.",
      "date": "2025-11-06T10:47:26+00:00"
    },
    {
      "id": 862717,
      "author": "Анна Анатольевна",
      "text": "У нас в регионе в последнее время Прокуратура подает  исковые заявления о признании сделки недействительной  только порядке ст.177ГК в интересах какой либо пенсионерки.\n\nДалее, суд по ходатайстау прокуратуоы быстро допрашивает родственников бабушек,  те сообщают суду \"архиважные\" сведения о том, что оказывается \"бабушка\" давно и глубоко больна (страдает  забывчивостью,  невнимате-стью)..при этом, она \" так больна\", что  последний раз была в поликлинике лет 8 назад и то просто забрать рецепт\n\nДалее, бабушка быстро проходит мрт, кт, невролога.\n\n Практическм всегда появляются  некие вполне естествнннве диагнозы для лиц старше 50 л саязанные с сосудами\n\nТакже быстро проводится психолого- психиатрическая экспертиза, которая делает вывод что бабушка на момент сделки страдала псих.заболевание,  давность возникновения которого  установить они не могут..но в анамнезе у нее ишемическая болезнь от 2005 года, гепертония , она \"плохо\" выполнила контрольные тесты  на экспертизе, плюс у нее психологич. особенности \"внушаемость, эмоциональность, сниженно  критическое мышление\".И все это в совокупности дает основание пологать экспертам о ее \"невменяемости\" в момент сделки.Все.\n\n Процесс окончен удовлетворением иска Прокуратуры.\n\nОтветчиков особенно никто и не слушает, как говорят судьи \" а что Вы можете сказать и что будете доказывать? \" экспертиза покажет что Истец невменяем , все. точка\n\nИ тут действительно возникает вопрос, зачем Ответчику собственно ходить в  суд ? Доказывать и аппелировать то ему нечем)) \n\nТолько слабо возразить об обьективности выводов экспертизы и проведении повторной, потому что ставить псих заболевание непонятного генезиса и давности только на основе показаний родни и наличии гипертонии,  весьма сомнительно, так можно признать каждого кто старше 50-55 лет...но и тут Истцы \"опережают\")), несут заключения врачебной комиссии : летать  запрещенно, ведь у нее гипертония и вообще ...\n\nС Камчатки \"выбраться\" можно только \"самолетом\"....\n \nвот и весь процесс против которого \"не пойдешь\"((",
      "date": "2025-11-06T10:36:29+00:00"
    },
    {
      "id": 862716,
      "author": "Максим Шедогубов",
      "text": "К моему глубокому сожалению, я имею сомнительное удовольствие знать Добровинского лично. К счастью, знакомство шапочное и сиюминутное, дольше я бы себя от членовредительства не удержал. Такого (из уважения к Роману удалено) не должно быть не только в адвокатуре, а даже в одном общественном туалете с приличными людьми. Однако, неоднократно лишенный статуса без проблем его восстанавливает. Видимо, что-то с фильтром не то. Забился",
      "date": "2025-11-06T10:35:42+00:00"
    },
    {
      "id": 862715,
      "author": "Cave Dweller",
      "text": "энергично моются кости адвокатов",
      "date": "2025-11-06T10:33:31+00:00"
    },
    {
      "id": 862714,
      "author": "Sorgenfrei",
      "text": "А что в случаях с ними было не так? В их действиях нашли дисциплинарные нарушения, применили   наиболее строгую меру ответственности - прекращение статуса. Расстрела за нарушение кодекса профэтики не предусмотрено🤷‍♂️Как видим, контроль обеспечен.",
      "date": "2025-11-06T10:29:59+00:00"
    },
    {
      "id": 862712,
      "author": "Nikita Ivankov",
      "text": "По комиссии: ну поступит жалоба, рассмотрят.\nПо экзамену: я считаю его минимальной проверкой на адекватность.\nКонкретно долбить человека за непрофессионализм из-за одного поста/темы я бы не стал",
      "date": "2025-11-06T10:29:17+00:00"
    },
    {
      "id": 862711,
      "author": "Anr",
      "text": "В сфере гражданского права кроме кого бы вы отметили? Кроме Скловского. А... Ю. Тай ?",
      "date": "2025-11-06T10:28:56+00:00"
    },
    {
      "id": 862709,
      "author": "Максим Шедогубов",
      "text": "Безусловно Вы правы. Пашаев и, прости Господи, Добровинский яркие тому примеры ;)",
      "date": "2025-11-06T10:27:41+00:00"
    },
    {
      "id": 862707,
      "author": "Антон",
      "text": "В отношении них самих?)",
      "date": "2025-11-06T10:23:34+00:00"
    },
    {
      "id": 862706,
      "author": "Василий Иванов",
      "text": "Если «профессиональными» юристами предлагают считать только адвокатов, то давайте считать тогда «профессиональными» адвокатами только тех, у которых есть в практике оправдательные приговоры",
      "date": "2025-11-06T10:23:14+00:00"
    },
    {
      "id": 862705,
      "author": "Максим Шедогубов",
      "text": "Смотрите тут какое дело. Я вот ни черта не смыслю в уголовном праве. И, в том числе поэтому, не раздаю советы в этой области права. Тем более, публичные. Заметьте, я не адвокат, Бог миловал. Мне не нужна дубинка в виде дисциплинарной комиссии, чтобы так не делать. Мне достаточно совести, воспитания и здравого смысла. А данный персонаж давать советы, глупость которых очевидна, не стесняется. Причем, чтобы понять это,  достаточно вдумчиво прочитать саму норму и хотя бы на 5 минут погрузиться в практику её применения. Да и знание доктрины хотя бы на уровне твердой тройки приличного ВУЗа точно убережет от такого вывода. Это что же получается? Адвокатский экзамен — пшик и профанация? Дискомиссия — тоже? Что же делать, что же делать…",
      "date": "2025-11-06T10:22:13+00:00"
    },
    {
      "id": 862702,
      "author": "Andrey Gordienko",
      "text": "Думаю, что авдвокат имел в виду, что то из этой категории:\n\nhttps://pgr--spb.sudrf.ru/modules.php?name=sud_delo&srv_num=1&name_op=case&case_id=821635806&case_uid=36eaee6c-f088-4ee6-9479-aef890577481&delo_id=1540005\n\nНо журналисты его не до конца поняли и растиражировали по всей сети, так как тема сейчас в активном тренде)",
      "date": "2025-11-06T10:15:30+00:00"
    },
    {
      "id": 862695,
      "author": "Максим Шедогубов",
      "text": "И я знаю. Но статус там ни при чем. И даже значок ни при чем. Просто, так совпало",
      "date": "2025-11-06T10:03:00+00:00"
    },
    {
      "id": 862690,
      "author": "Ёжег",
      "text": "Роман Сергеевич , извиняюсь. Сразу поправил , мат исключен",
      "date": "2025-11-06T09:57:57+00:00"
    },
    {
      "id": 862689,
      "author": "Roman Bevzenko",
      "text": "Это не так. Я знаю много адвокатов - блестящих юристов.",
      "date": "2025-11-06T09:57:48+00:00"
    },
    {
      "id": 862685,
      "author": "Максим Шедогубов",
      "text": "Ну позвольте с Вами не согласиться, дорогой друг. Статус адвоката гарантирует, что а) обладатель сего внес в кассу палаты по прайсу за вступление, б) продолжает по прайсу исправно платить. Других там не держат. А еще у него есть значок 😉",
      "date": "2025-11-06T09:55:56+00:00"
    },
    {
      "id": 862682,
      "author": "Sorgenfrei",
      "text": "Вопрос в уровне относительно всего рынка, который представлен не исключительно ведущими фирмами, но и людьми вовсе без образования, психически больными и пр. Адвокатский статус предполагает наличие входных фильтров в профессию, но ждать от каждого адвоката блестящих знаний - это утопия. В конкретном кейсе возможно предположить будто бы ответчик имел возможность выбирать представителей из широкого круга специалистов высочайшей квалификации. В иных случаях люди выбирают между «ужасно» и «плохо». Адвокатский статус предполагает, что есть контроль до уровня «не ужасно»",
      "date": "2025-11-06T09:55:09+00:00"
    },
    {
      "id": 862681,
      "author": "tolyan",
      "text": "100%, он видимо никогда не взыскивал убытки с Минфина. Мне лично это удавалась, но после отмены отказа в кассации. Это безумно сложная категория дел",
      "date": "2025-11-06T09:54:35+00:00"
    },
    {
      "id": 862680,
      "author": "Roman Bevzenko",
      "text": "Или вы удаляете свой предыдущий пост, или в бан отправлю за нарушение правил",
      "date": "2025-11-06T09:54:16+00:00"
    },
    {
      "id": 862679,
      "author": "Liliya",
      "text": "Голова для шапки, а рот для того, чтобы им есть)",
      "date": "2025-11-06T09:54:12+00:00"
    },
    {
      "id": 862678,
      "author": "Ёжег",
      "text": "Ну если спроецировать подход Мосгорсуда по делу Долиной , то деньги не возвращаем, так как деньги у продавца похитили третьи лица , а квартиру не возвращаем , так как квартиру у покупателя тоже похитили третьи лица 😂",
      "date": "2025-11-06T09:52:56+00:00"
    },
    {
      "id": 862676,
      "author": "Владислав Катасонов",
      "text": "Эту компенсацию по ст. 68.1 ещё попробуй получи.",
      "date": "2025-11-06T09:52:38+00:00"
    },
    {
      "id": 862675,
      "author": "I B",
      "text": "Если человек дает такой совет, то он экспертом не является ни в чем вообще",
      "date": "2025-11-06T09:52:04+00:00"
    },
    {
      "id": 862673,
      "author": "Максим",
      "text": "незаключенность договора",
      "date": "2025-11-06T09:50:47+00:00"
    },
    {
      "id": 862672,
      "author": "Ivan",
      "text": "Шутка шуткой, но что меняется, если порок воли не только у продавца, но и у покупателя?)",
      "date": "2025-11-06T09:49:31+00:00"
    },
    {
      "id": 862670,
      "author": "Nikita Ivankov",
      "text": "Я не знаю этого человека, его адвокатское образование, палату, членов квал комиссии. Ну, из исходных данных у меня нет выводов о «подкупном» характере его собеседования в палате (если вы об этом). Если вы о слабом отсеве, на том же ПМЮФ Володина, Резник говорили о том, что адвокатский экзамен-это минимальный по требованиям проверочный механизм, человек не обязан быть экспертом во всём. В Новосибирске экзамен сдает 60% примерно. С фразой Чучейко не знаком, на практике она не соответствует действительности.",
      "date": "2025-11-06T09:48:25+00:00"
    },
    {
      "id": 862669,
      "author": "Ascetic",
      "text": "Ахаха, браво! 👏 как раз на просторах сети видел этот треш от «адвоката»! Провели лицом об тейбл))))",
      "date": "2025-11-06T09:47:59+00:00"
    },
    {
      "id": 862668,
      "author": "Roman Bevzenko",
      "text": "Предупреждение за нарушение правил. Мат запрещен. Удаляйте",
      "date": "2025-11-06T09:47:51+00:00"
    },
    {
      "id": 862667,
      "author": "Ёжег",
      "text": "Молодой адвокат спрашивает опытного:\n— Можете, пожалуйста, наглядно объяснить, что такое правовая лакуна?\n— Ну смотри. Покупает бабка квартиру у бабки. После чего начинается суд, где бабка истец заявляет, что она была одурманена мошенниками и не отдавала отчета при продаже квартиры, а бабка ответчик заявляет, что она тоже была одурманена и не отдавала отчете при покупке квартиры, после чего судья закрывает суд на амбарный замок, потому что ни к чему такие парадоксы",
      "date": "2025-11-06T09:46:51+00:00"
    },
    {
      "id": 862665,
      "author": "tolyan",
      "text": "Это черный пиар",
      "date": "2025-11-06T09:45:01+00:00"
    },
    {
      "id": 862659,
      "author": "Liliya",
      "text": "Ещё хуже, что такой совет разошёлся  по пабликам. Я была изрядно удивлена пофигизмом тех, кто далее транслировал эту гениальную мысль в массы.",
      "date": "2025-11-06T09:40:25+00:00"
    },
    {
      "id": 862658,
      "author": "Nikita Ivankov",
      "text": "Согласен полностью с вами в этой части",
      "date": "2025-11-06T09:38:23+00:00"
    },
    {
      "id": 862657,
      "author": "Максим Шедогубов",
      "text": "Скажите, уважаемый Никита, а как такой, гм, «специалист» сумел прорваться сквозь безусловно неподкупный, строгий и справедливый профессиональный фильтр адвокатского экзамена? Не наше ли ясно солнышко г-н Чуйченко на голубом глазу утверждал, что диплом юрфака да, не решает, а вот экзамен — мерило из мерил! Что ж делать — что ж делать? Поздравлять господина соврамши?",
      "date": "2025-11-06T09:37:21+00:00"
    },
    {
      "id": 862656,
      "author": "Антон",
      "text": "Связан тем, что изменения в проц.кодексы мотивируются профессионализмом адвокатов. Любое проявление ими непрофессионализма показывает несостоятельность этого довода",
      "date": "2025-11-06T09:36:00+00:00"
    },
    {
      "id": 862655,
      "author": "Roman Bevzenko",
      "text": "меня бесит, когда сторонники адвокатской монополии утверждают, что статус адвоката гарантирует качество юридической помощи. Ничего он не гарантирует",
      "date": "2025-11-06T09:35:56+00:00"
    },
    {
      "id": 862654,
      "author": "Nikita Ivankov",
      "text": "Странно прям в заголовке поста писать «в догонку про профессиональные качества адвокатского корпуса». Это как будто довод «сейчас я покажу, какой корпус гнилой». \nЕсть конкретный человек, он делает такие-то действия. Он входит в институт, состоящий из нескольких десятков тысяч человек. Он не лидер мнений, не юридически авторитет/руководитель. \nКонкретно по существу, он не прав, более того, как будто рекламирует себя через неверное толкование нормы права, что не очень) \nНо, заголовок все же не очень связан с содержанием поста)",
      "date": "2025-11-06T09:33:21+00:00"
    },
    {
      "id": 862653,
      "author": "Марк 🍉 Сутяга",
      "text": "как говаривал один известный юрист и учёный: \"привет адвокатской монополии\"",
      "date": "2025-11-06T09:33:01+00:00"
    },
    {
      "id": 862651,
      "author": "Иван Еремеев",
      "text": "Ох уж эти адвокаты, скажу я вам",
      "date": "2025-11-06T09:31:36+00:00"
    },
    {
      "id": 862650,
      "author": "KK",
      "text": "Ст. 68.1 применяется, к примеру, если были подделаны документы и на их основании внесена запись в реестр, а в дальнейшем продана недвижимость?",
      "date": "2025-11-06T09:31:27+00:00"
    },
    {
      "id": 862649,
      "author": "Roman Bevzenko",
      "text": "собственно, одна из причин, почему я в свое время не стал адвокатом - это удивительная безграмотность бОльшей части адвокатов, которые меня окружали во время работы в адвокатском бюро. Хотя были и мэтры, которые вызывали у меня восхищение!",
      "date": "2025-11-06T09:30:54+00:00"
    },
    {
      "id": 862648,
      "author": null,
      "text": "Смотрели практику применения этой статьи, очень спорно и много отказов\nПлюс компенсация мб в зависимости от кадастровой цены,а не указанной в договоре",
      "date": "2025-11-06T09:30:53+00:00"
    },
    {
      "id": 862647,
      "author": "Igor K",
      "text": "Так это же совет, а не консультация 😁\nПравда совет у адвоката может быть только один - обратиться за консультацией 😁. Значит это и не совет вовсе, а заполнение сайта",
      "date": "2025-11-06T09:30:53+00:00"
    },
    {
      "id": 862646,
      "author": "Toritta Moscovia",
      "text": "Только вчера этот опус читала)",
      "date": "2025-11-06T09:29:27+00:00"
    },
    {
      "id": 862645,
      "author": "Максим Шедогубов",
      "text": "Роман, ну что же Вы сегодня так с адвокатами. На святое покусились. На гешефт :)",
      "date": "2025-11-06T09:29:17+00:00"
    },
    {
      "id": 862644,
      "author": "Danil",
      "text": "Роман Сергеевич, нужно уже энциклопедию \"советов\" адвокатов делать, чтобы в МинЮст её предоставить для обсуждения монополии",
      "date": "2025-11-06T09:28:13+00:00"
    },
    {
      "id": 862643,
      "author": "Анна Позднякова",
      "text": "Спасибо большое за ваш комментарий, Роман Сергеевич 🤝",
      "date": "2025-11-06T09:28:12+00:00"
    }
  ]
}