{
  "post_id": 2834,
  "updated_at": "2026-03-11T20:32:58.201315+00:00",
  "comments": [
    {
      "id": 864367,
      "author": "Евгений Имангулов |Страховой Юрист",
      "text": "Президиум отменит. Смеяться\n\nПрезидиум под руководством этатиста Краснова отменит. \n\nСмеяться вдвойне",
      "date": "2025-11-13T03:53:42+00:00"
    },
    {
      "id": 864310,
      "author": "Владислав Катасонов",
      "text": "Friendly fire",
      "date": "2025-11-12T14:40:42+00:00"
    },
    {
      "id": 864278,
      "author": "Ирина Сапрыгина",
      "text": "Минэкологии МО ответ на антикоррупционную экспертизу написало именно в таких выражениях еще аж в 2019 году. В суде потом, конечно, поржали, когда я это с выражением зачитала и попросила представителя Минэкологии пояснить, что же это здесь изложено, в официальном ответе... Каким было решение суда, полагаю, догадываетесь",
      "date": "2025-11-12T13:36:00+00:00"
    },
    {
      "id": 864175,
      "author": "Петр",
      "text": "Я бы упростил : подавать заявления только через Госуслуги а рассматривать их будет алгоритм Макс и тут же выдавать решения/скрипты, работает 24/7 без зарплаты и выходных. Услуга оказана поставьте оценку оказаной услуги.😁",
      "date": "2025-11-12T10:01:09+00:00"
    },
    {
      "id": 864172,
      "author": "Мария А.",
      "text": "Ну придумают что-то типа штампа \"Удовлетворить. Вступило в силу. Исполять\", который будут проставлять сразу на заявлениях....\nДелов-то 🤷‍♀",
      "date": "2025-11-12T09:56:49+00:00"
    },
    {
      "id": 864163,
      "author": "Sergey Prokopiev",
      "text": "Вы думали это просто так в судах висит?",
      "date": "2025-11-12T09:55:14+00:00"
    },
    {
      "id": 864162,
      "author": "Петр",
      "text": "Могут быть и сбои по техническим причинам : по словам генерального директора Судебного департамента при Верховном суде Владислава Иванова, некомплект в кадрах среди федеральных и мировых судей в России достиг 20 % от общего числа судейского корпуса",
      "date": "2025-11-12T09:54:20+00:00"
    },
    {
      "id": 864161,
      "author": "Ignat",
      "text": "Ключевое слово «пока». Если нужно будет сажать массово, то могут и возродить славные традиции. Вопрос только в том, где взять такое количество врагов народа, ведь на последних выборах главный кандидат набрал в районе 90%",
      "date": "2025-11-12T09:52:54+00:00"
    },
    {
      "id": 864159,
      "author": "Мария А.",
      "text": "На внесулебный порядок, думаю, не пойдут пока\nДа и зачем? \nСудебная система прекрасно работает, так как нужно. Только наконец-то отладили можно сказать 😎",
      "date": "2025-11-12T09:48:44+00:00"
    },
    {
      "id": 864158,
      "author": "Петр",
      "text": "27 мая 1935 года приказом наркома внутренних дел СССР № 00192 для внесудебного рассмотрения дел были созданы областные тройки НКВД.",
      "date": "2025-11-12T09:45:45+00:00"
    },
    {
      "id": 864157,
      "author": "Мария А.",
      "text": "Я об этом еще год назад писала =)\nНо более реальное предположение - выделение особой категории исков с максимально упрощенным порядком ~рассмотрения~ удовлетворения в порядке какой-нибудь новой главы процессуальеых кодексов. Шах и мат.\nТак будут пресечены все эти наши \"возмущения на вдохе\" 😁",
      "date": "2025-11-12T09:43:08+00:00"
    },
    {
      "id": 864155,
      "author": "Serg Mo",
      "text": "Ну и потом, любитель карт 16 века пишет же в своих пасквилях, что государство является благом, подлежащим отдельной защите. И вот как у них так получается, то они ставят общественное превыше частного, а то ограничивают в правах десятки миллионов людей, чтобы якобы поймать несколько сотен мошенников телефонных.",
      "date": "2025-11-12T09:39:30+00:00"
    },
    {
      "id": 864154,
      "author": "Владислав Катасонов",
      "text": "Интересно, дойдёт когда-нибудь до того, что прокуроры свои иски будут обосновывать необходимостью достижения целей сво?)",
      "date": "2025-11-12T09:38:42+00:00"
    },
    {
      "id": 864146,
      "author": "Ирина",
      "text": "Нет. Это специальные задачи для уполномоченных на то законом органов и должностных лиц. Если эти задачи выполняют все вокруг, то они выходят за пределы своих полномочий. Чего стоит интернет-скандал, где группа женщин решила, что они теперь борцы за справедливость и государственную безопасность. Для них это на данном этапе закончилось возбуждением дела об административном правонарушении",
      "date": "2025-11-12T09:18:22+00:00"
    },
    {
      "id": 864145,
      "author": "სერხიო",
      "text": "Я уже на работе сообщил руководителям, что они могут лишиться имущества своего, достаточно прокуратуре заявить, что они крышуют проституток. Доказательством является само заявление прокуратуры",
      "date": "2025-11-12T09:17:50+00:00"
    },
    {
      "id": 864144,
      "author": "Serg Mo",
      "text": "Ну, многие \"уголовники\" говорят же о том, что у следствия свои УПК, например. Тогда и Прокурорскую конституцию надо где то опубликовать.",
      "date": "2025-11-12T09:17:03+00:00"
    },
    {
      "id": 864140,
      "author": "Ирина",
      "text": "Очередной судебный акт, демонстрирующий несоответствие функции, выполненной судом, задачам арбитражного судопроизводства. \"Защита национальных интересов\", в моем споре – защита экономической безопасности. Но эти задачи не поименованы в АПК РФ, и суд выполняет не свойственную ему функцию",
      "date": "2025-11-12T09:13:21+00:00"
    },
    {
      "id": 864138,
      "author": "👁",
      "text": "Принцип равенства участников)",
      "date": "2025-11-12T09:09:34+00:00"
    },
    {
      "id": 864134,
      "author": "Ignat",
      "text": "Может пора уже создать какой-нибудь Прокурорский процессуальный кодекс? Ну чтобы не заморачиваться сильно в таких (да и не только) делах. Ввести презумпцию безусловной обоснованности любых ходатайств и заявлений прокурора, переложив бремя доказывания необоснованности на ответчиков. Видно же что сильно мешает законодательство прокуратуре. Понаписали там либералы в 90-е и 2000-е всякой всячины, а теперь надо напрягаться",
      "date": "2025-11-12T09:05:29+00:00"
    },
    {
      "id": 864133,
      "author": "Konstantin",
      "text": "Почему сразу советское? При Сталине такого безобразия не было. Это волюнтарист Хрущёв всех  со своими новыми кодексами пораспустил.",
      "date": "2025-11-12T09:05:28+00:00"
    },
    {
      "id": 864132,
      "author": "Евгений Шмаков",
      "text": "Получается, что у нас в целом складывается ряд правовых норм, начиная с некоторых норм Конституции, которые записаны, но в действительности применению не подлежат. То есть, в рассматриваемых делах суд их будет «не видеть»🤔\nДумаю, что это должно производить гнетущее ощущение на судей.",
      "date": "2025-11-12T09:03:45+00:00"
    },
    {
      "id": 864130,
      "author": "ᅠ ᅠ ᅠ ᅠ",
      "text": "а почему право «русское», а не российское……",
      "date": "2025-11-12T09:02:10+00:00"
    },
    {
      "id": 864129,
      "author": "Василий Розанов",
      "text": "ну все, приехали",
      "date": "2025-11-12T08:59:34+00:00"
    },
    {
      "id": 864128,
      "author": "Петр",
      "text": "Как и писал ранее строить гос деды будут свое прошлое а построят кривое настоящее. Печально",
      "date": "2025-11-12T08:58:57+00:00"
    },
    {
      "id": 864127,
      "author": "Grace Divine ;)",
      "text": "Убежденная вера в Президиум может, как мне кажется, основываться только на принципе сredo quia absurdum est.🙈",
      "date": "2025-11-12T08:58:06+00:00"
    }
  ]
}