{
  "post_id": 2854,
  "updated_at": "2026-03-11T20:32:58.195632+00:00",
  "comments": [
    {
      "id": 866380,
      "author": "Адвокат Мамаева Элен Москва",
      "text": "Если есть, дайте, пожалуйста, ссылку на какой-нибудь текст (статью, книгу, отзыв на исковое заявление) из-под Вашего пера)) хочу услышать музыку Вашей речи (без сарказма)",
      "date": "2025-11-22T16:18:04+00:00"
    },
    {
      "id": 866344,
      "author": "Александра Шульц",
      "text": "Да скорее наоборот, там такой светло-серый трикотаж пижамного типа)",
      "date": "2025-11-22T10:48:21+00:00"
    },
    {
      "id": 866290,
      "author": "Eugen Heinrich",
      "text": "Мужской",
      "date": "2025-11-21T22:03:20+00:00"
    },
    {
      "id": 866289,
      "author": "RIK",
      "text": "Роман Сергеевич с волосами - ушла эпоха...",
      "date": "2025-11-21T22:02:53+00:00"
    },
    {
      "id": 866288,
      "author": "Виктория",
      "text": "Наши такое могут)) \nМеня всегда удивляло содержание судебных актов, которые выносят в наших краснодарских судах. Но до сих пор для меня останется загадкой, как при таких очевидных и грубевших ошибках люди сохраняют должность…? Хотя я догадываюсь💸",
      "date": "2025-11-21T20:51:06+00:00"
    },
    {
      "id": 866287,
      "author": "Тигр Лев",
      "text": "А если декольте, все инфаркт, инсульт",
      "date": "2025-11-21T20:23:00+00:00"
    },
    {
      "id": 866286,
      "author": "Daria",
      "text": "Не дай бог ещё каблук выше 5 см из-под мантии выглянет",
      "date": "2025-11-21T20:12:01+00:00"
    },
    {
      "id": 866284,
      "author": "Vasiliy",
      "text": "Лето, жара. \nСудья арбитражного или районного суда (уже не помню): \"с вашего позволения я разоблачусь\". И снял мантию.\nТак у нас в компании появилась шутка - разоблачение судьи.",
      "date": "2025-11-21T20:07:26+00:00"
    },
    {
      "id": 866283,
      "author": "I",
      "text": "Так, а существуют же \"Типовые правила пребывания посетителей в судах\", в которых прямо написано, что основаниями для отказа в допуске в здание (помещение) суда являются, в том числе прибытие в суд лиц в спортивной или пляжной одежде и обуви, в шортах выше колен.\n\nP.S. Когда впервые довелось попасть в судебное СКЭС ВС РФ, сильно удивили распущенные волосы председательствующей...",
      "date": "2025-11-21T19:56:10+00:00"
    },
    {
      "id": 866280,
      "author": "Алексей Кычин",
      "text": "Им проще. Это сотрудники аппарата обязаны на работе форму носить, кители и всё такое. Я много раз видел: у судьи сверху мантия, а ниже - джинсы и кроссовки.",
      "date": "2025-11-21T18:45:48+00:00"
    },
    {
      "id": 866276,
      "author": "Алексей Кычин",
      "text": "О, я представляю, она такая чёткая на заседании была )",
      "date": "2025-11-21T18:40:15+00:00"
    },
    {
      "id": 866274,
      "author": "Serg Mo",
      "text": "Если в запорожец поставить руль от мерседеса, то мерседесом он не станет.",
      "date": "2025-11-21T18:36:58+00:00"
    },
    {
      "id": 866270,
      "author": "Robert Maksotckii",
      "text": "Прикольнее, если бы пришел в гидрокостюме, в ластах и с морским ружьем. Прямо после подводной охоты.",
      "date": "2025-11-21T17:53:28+00:00"
    },
    {
      "id": 866268,
      "author": "Eisbreсher_Lenin",
      "text": "Разве в этом нельзя в суд?",
      "date": "2025-11-21T17:41:06+00:00"
    },
    {
      "id": 866267,
      "author": "Ангелина",
      "text": "Я помню в 90-е в старших классах по обмену ездили жить в США, я привезла оттуда такое красивые кружевные платья. Пошла на практику АС РФ, который только что создали, там судьи мужчины были рады нам молодым девчонкам практикантам, один дяденька судья даже ( сейчас председатель одного из кассационных судов, был моим защитником дипломной в универе). А вот, как мне тогда казалось пожилая тетя судья, встала и сказала ,,  я перед Вами в процессе не в купальнике сижу, так что и Вы в ночной рубашке не ходите в суд,, она даже не понимала, что это  американское платье)",
      "date": "2025-11-21T17:37:30+00:00"
    },
    {
      "id": 866263,
      "author": "Robert Maksotckii",
      "text": "Юрфак наш закупал (до 24/2, сейчас не знаю): интересно, сколько процентов студентов и преподавателей им пользовалось)))",
      "date": "2025-11-21T17:06:12+00:00"
    },
    {
      "id": 866262,
      "author": "Юлия",
      "text": "Доверитель через неделю после процесса звонит - ты случайной не взяла мой паспорт? Отмотали назад - а он в суд приехал, дэнди, в рабочей куртке с логотипом компании на спине, паспорт нашелся в кармане. Еще неделю вопил: неее, не может быть.                                                                                                  Летом в +35 сидим в процессе, запыхавшаяся помощница арбитражного управляющего: спасите- помогите, приставы не пускают управляющего, он в шортах. Судья, со стебом: в коротких? Меряли потом длину взглядами.                              И да, я тот представитель с тату на руках и ногах. Никогда не мешали.",
      "date": "2025-11-21T17:00:58+00:00"
    },
    {
      "id": 866255,
      "author": "Animal",
      "text": "О, да, рассматривать определения об составлении искового заявления без движения и о возврате иска отдельно и без взаимосвязи и по обоим выносить 2 отдельных апелляционных определения без учёта их взаимосвязи - это как нефик делать 🙃",
      "date": "2025-11-21T16:35:16+00:00"
    },
    {
      "id": 866254,
      "author": "Animal",
      "text": "Фрактальные бананы-наны",
      "date": "2025-11-21T16:27:56+00:00"
    },
    {
      "id": 866250,
      "author": "Eisbreсher_Lenin",
      "text": "Это надо содрать",
      "date": "2025-11-21T16:04:33+00:00"
    },
    {
      "id": 866249,
      "author": "Robert Maksotckii",
      "text": "А если там наколото: «продажные судьи»?",
      "date": "2025-11-21T16:02:32+00:00"
    },
    {
      "id": 866247,
      "author": "Vagan Minasian",
      "text": "Определение: Наколка — это термин, который часто используется для обозначения татуировок, сделанных в тюремной среде или среди определенных субкультур. Наколки могут иметь специфические значения и символику, связанные с жизнью в тюрьме.",
      "date": "2025-11-21T14:44:20+00:00"
    },
    {
      "id": 866241,
      "author": "Vagan Minasian",
      "text": "Само слово - \"наколка\"",
      "date": "2025-11-21T14:03:33+00:00"
    },
    {
      "id": 866239,
      "author": "Pavel Rogozhnikov",
      "text": "Надеюсь, не снимая мантии.",
      "date": "2025-11-21T13:52:58+00:00"
    },
    {
      "id": 866237,
      "author": "Федор",
      "text": "А он именно блэк играл или все же атмосферик пост-блэк?",
      "date": "2025-11-21T13:40:17+00:00"
    },
    {
      "id": 866235,
      "author": "Anastasia Milovskaya",
      "text": "Так уже, что такого ужасного в наколках)",
      "date": "2025-11-21T13:28:39+00:00"
    },
    {
      "id": 866233,
      "author": "Natalia D.",
      "text": "При мне девушку в никулинский суд не хотели пускать приставы в короткой юбке  . Причём девушка даже не в процесс шла, а на приём . И то была не баба, а шорты-юбка",
      "date": "2025-11-21T13:25:35+00:00"
    },
    {
      "id": 866221,
      "author": "Robert Maksotckii",
      "text": "Выдержки?",
      "date": "2025-11-21T11:47:33+00:00"
    },
    {
      "id": 866219,
      "author": "Вадим О́бвинцев",
      "text": "Скорее всего. Мне старичку всё кажется недавно, 10-15 лет ни о чем, как вчера",
      "date": "2025-11-21T10:51:58+00:00"
    },
    {
      "id": 866204,
      "author": "Eisbreсher_Lenin",
      "text": "18-летних",
      "date": "2025-11-21T10:21:38+00:00"
    },
    {
      "id": 866203,
      "author": "Robert Maksotckii",
      "text": "Сборник шотландско-правовых прецедентов!",
      "date": "2025-11-21T10:16:32+00:00"
    },
    {
      "id": 866194,
      "author": "Igor Z",
      "text": "«Слева Ленин справа Сталин, ну на этой, чем сижу.»",
      "date": "2025-11-21T09:30:46+00:00"
    },
    {
      "id": 866192,
      "author": "Александр Сорокопуд",
      "text": "А чего такой печальный взгляд? От тяжести бремени бытия?",
      "date": "2025-11-21T09:25:18+00:00"
    },
    {
      "id": 866188,
      "author": "Вадим О́бвинцев",
      "text": "Это вопрос культуры, этики, и традиций. Ну и конечно регламентов и дрескодов",
      "date": "2025-11-21T09:06:51+00:00"
    },
    {
      "id": 866185,
      "author": "Pavel Rogozhnikov",
      "text": "У меня как-то специалист-гидролог приперся в бриджах до середины икры и сандалиях. Хорошо, что удалось аккуратно войти и разместить его за столом прямо у входа, где этот позор не было видно, даже когда он вставал для выступления.",
      "date": "2025-11-21T08:53:16+00:00"
    },
    {
      "id": 866178,
      "author": "Виктория",
      "text": "«Южная судебная аномалия»🤣",
      "date": "2025-11-21T08:46:18+00:00"
    },
    {
      "id": 866177,
      "author": "Вадим О́бвинцев",
      "text": "Не, я в шортах видел в Краснодаре в АС, летом +38 - специфика региона. Но в коридоре было холодно.",
      "date": "2025-11-21T08:44:44+00:00"
    },
    {
      "id": 866176,
      "author": "cobr cobr",
      "text": "По-моему, судьи в АГСМ уже ко всему привычные. Как-то летом видел там представителя  в короткой футболке с тату в виде рун на обеих руках. Замечания судья не делал. Вроде как кого-то в шортах-бермудах не допустили в процесс, но это только понаслышке.",
      "date": "2025-11-21T08:41:54+00:00"
    },
    {
      "id": 866175,
      "author": "Вадим О́бвинцев",
      "text": "Когда уже изобретут банану- нану, чтобы одежда вообще стала не нужна, а свой облик мы формировали в приложении как оболочку и могли ее менять на ходу. Еще и шапку-невидимку в придачу по вип-подписке -  пожалуйста!",
      "date": "2025-11-21T08:39:41+00:00"
    },
    {
      "id": 866174,
      "author": "Vagan Minasian",
      "text": "Толи дело быть представителем в судах России. Судьи - высшая ступень эволюции, Минюст со своей адвокатской монополией, ФПА, потирающий руки, ну и как вишенка на торте - прокурор в должности председателя Верховного Суда.",
      "date": "2025-11-21T08:30:43+00:00"
    },
    {
      "id": 866173,
      "author": "Dr. VinSer",
      "text": "Не хотел бы я лично быть английским барристером в наши дни. Тяжелая и мало оплачиваемая работа, с жестокой конкуренцией и крайне узкой сферой деятельности - представление интересов клиентов в высших судах: Королевские суды, Высокий суд Англии и Уэльса, Апелляционный суд Англии и Уэльса и Верховный суд Великобритании. Не разгуляешься в общем. UPD: кстати, книги на заднем фоне это типичное издание прецедентов в той или иной области. Толку от них в современном мире мало, так как все пользуются или West Law или Nexis Lexis. Но для антуража они стоят практически в каждом юридическом офисе.",
      "date": "2025-11-21T08:26:53+00:00"
    },
    {
      "id": 866168,
      "author": "Ирина",
      "text": "За десять-пятнадцать лет уже и забылось, как судьи вели процессы в цивильной одежде:))",
      "date": "2025-11-21T08:19:24+00:00"
    },
    {
      "id": 866167,
      "author": "Jane",
      "text": "Подкрадули это святое. Попробуйте из одного суда в другой за два дня в разных регионах, на самолётах. Только подкрадули и джинсы спасают.",
      "date": "2025-11-21T08:19:24+00:00"
    },
    {
      "id": 866166,
      "author": "Мария А.",
      "text": "О да. В психологии это как-то называется, забыла как\nФорменная одежда в памяти остается, а лиц не запоминают. Врачи, полиционеры, судьи, работники жилконтор =)))\nЯ так судью в неформальном баре встретила. А он еще и хвост носил 😁",
      "date": "2025-11-21T08:16:44+00:00"
    },
    {
      "id": 866164,
      "author": "Vagan Minasian",
      "text": "А что в челлендже никто больше не участвует? Nano Banano pro кстати как и ожидалось отличная вышла!",
      "date": "2025-11-21T08:09:05+00:00"
    },
    {
      "id": 866162,
      "author": "Aleksei Solomyanyi",
      "text": "С поездки не успел переодеться, на заседании был в кроссовках красного цвета. Стыдно было. Потом стыд исчез, когда правосудие явно на стороне ответчика (застройщик)",
      "date": "2025-11-21T08:03:43+00:00"
    },
    {
      "id": 866159,
      "author": "Paul McBear",
      "text": "А отчего ромеи стали придерживаться пунической традиции письма без гласных?",
      "date": "2025-11-21T07:28:57+00:00"
    },
    {
      "id": 866158,
      "author": null,
      "text": "Когда смотрел видеозаписи \"московских процессов\", проходивших в рамках ст*л*нск*х р*пр*сс*й (осуждаю), всегда было интересно, что там судьи были в военной форме, а обвинитель - в гражданском костюме",
      "date": "2025-11-21T07:26:04+00:00"
    },
    {
      "id": 866157,
      "author": "Людмила Леонова",
      "text": "Вам очень идёт, Роман Сергеевич.",
      "date": "2025-11-21T07:20:03+00:00"
    },
    {
      "id": 866156,
      "author": "Александра Ерш",
      "text": "Так нет проблем, адвокатура давно мантии внедряет в жизнь. :) Без парика, конечно. Но выглядит сия одёжа весьма чинно и основательно.",
      "date": "2025-11-21T07:20:01+00:00"
    },
    {
      "id": 866155,
      "author": "Александр Малютин",
      "text": "Подтверждаю. Это довольно необычно наблюдать с точки зрения восприятия. Был однажды в суде, вдруг со мной здоровается стильно одетый парень. Приветливый такой. Сначала не понял кто это, потом понял, что это же судья))",
      "date": "2025-11-21T07:18:29+00:00"
    },
    {
      "id": 866154,
      "author": "Роман",
      "text": "на лицо мантию не натянешь",
      "date": "2025-11-21T07:17:46+00:00"
    },
    {
      "id": 866152,
      "author": "Денис",
      "text": "В АСгМ если присмотреться , то половина судей-мужчин в кроссовках формата \"подкрадухи\", сетчатых на мягкой подошве, думаю что и под мантиями сплошной casual. Так что это там такой общий тренд)",
      "date": "2025-11-21T07:11:15+00:00"
    },
    {
      "id": 866151,
      "author": "Александра Шульц",
      "text": "Вообще всякое бывает. У нас по одному делу представитель одного из участников ехала из одной командировки сразу в другую, домой ненадолго забежала и забыла там сумку с одеждой. Ну была в спортивном костюме, в котором ехала)",
      "date": "2025-11-21T07:08:45+00:00"
    },
    {
      "id": 866150,
      "author": "0,999…",
      "text": "Купола только для апелляции и выше!\nВ ВС можно слева профиль Сталина (а справа Маринка анфас).",
      "date": "2025-11-21T07:08:01+00:00"
    },
    {
      "id": 866148,
      "author": "Денис",
      "text": "Судьям с этим проще, они в мантиях. Это я к тому, что весьма скоро нас ждёт поколение судей с наколками.",
      "date": "2025-11-21T07:06:15+00:00"
    },
    {
      "id": 866147,
      "author": "Alexandr",
      "text": "😁",
      "date": "2025-11-21T07:03:38+00:00"
    },
    {
      "id": 866146,
      "author": "0,999…",
      "text": "Как-то в АСГМ представитель налоговой (по-моему, УФНС даже) зашел в пальто.\n- Разденьтесь, - говорит судья. - Да не здесь, здесь не гардероб.\nПарень этот вышел в коридор и вернулся в обтягивающей рубашке поло; но судью, на мой взгляд, не это убило, а многочисленные наколки на руках. Она подумала и говорит:\n- Нет, все-таки оденьтесь.\nТак он и сидел в пальто.",
      "date": "2025-11-21T07:00:55+00:00"
    },
    {
      "id": 866145,
      "author": "Денис",
      "text": "Standart Slavic Face на месте",
      "date": "2025-11-21T07:00:35+00:00"
    },
    {
      "id": 866143,
      "author": "Александр Лазарев",
      "text": "В глазах чувствуется тоска по уютным коридорам Чертановского районного суда)",
      "date": "2025-11-21T06:58:02+00:00"
    },
    {
      "id": 866142,
      "author": "Павел Мищенко",
      "text": "Кто в теме тот в теме😁",
      "date": "2025-11-21T06:55:25+00:00"
    },
    {
      "id": 866140,
      "author": "Liliya",
      "text": "#пятничное",
      "date": "2025-11-21T06:52:26+00:00"
    },
    {
      "id": 866139,
      "author": "Виталий",
      "text": "А хорошо бы чтоб и у нас так можно было в народный суд : чинно , основательно , культурно .",
      "date": "2025-11-21T06:51:57+00:00"
    },
    {
      "id": 866138,
      "author": null,
      "text": "Было бы интересно проверить, какая будет реакция, если представителю стороны прийти так на заседание в российский суд",
      "date": "2025-11-21T06:51:51+00:00"
    },
    {
      "id": 866137,
      "author": "Миша",
      "text": "Что за книги, по мнению нейросети, стоят на фоне?) И почему они (слева)так странно поставлены?)",
      "date": "2025-11-21T06:50:53+00:00"
    },
    {
      "id": 866132,
      "author": "Elias",
      "text": "Это английский суд?",
      "date": "2025-11-21T06:47:57+00:00"
    }
  ]
}