{
  "post_id": 2986,
  "updated_at": "2026-03-11T20:32:58.153690+00:00",
  "comments": [
    {
      "id": 887788,
      "author": "Илья Ильичев",
      "text": "Жив шаблон, с которого писали 😂",
      "date": "2026-02-20T17:46:07+00:00"
    },
    {
      "id": 887644,
      "author": "Валерий Ржановский",
      "text": "Дело живёт",
      "date": "2026-02-20T07:59:25+00:00"
    },
    {
      "id": 887642,
      "author": "Евгений",
      "text": "\"Судьи ВАС\" приходят в эконом.коллегию ВС и говорят, что ее не существует потому, что она зарегистрирована как фирма на Багамских островах",
      "date": "2026-02-20T07:11:04+00:00"
    },
    {
      "id": 887639,
      "author": "Aw",
      "text": "Жаль, что нет описок в Консультанте? Нужны?",
      "date": "2026-02-20T06:56:38+00:00"
    },
    {
      "id": 887638,
      "author": "Станислав Петрович",
      "text": "Дайте ВАС — требуют наши сердца\nДайте ВАС — требуют наши глаза\nВ наших мыслях и в наших слезах — ВАС\nТолько ВАС! Мы ждём только ВАС!",
      "date": "2026-02-20T06:53:57+00:00"
    },
    {
      "id": 887637,
      "author": "Роман Яковлев",
      "text": "ВАС периодически шкерится, словно его признали иноагентом и иногда выходит из тени. А если серьёзно как такое может быть?",
      "date": "2026-02-20T06:52:02+00:00"
    },
    {
      "id": 887636,
      "author": "arrrttuur",
      "text": "теперь решил перейти на уголовные дела",
      "date": "2026-02-20T06:50:00+00:00"
    },
    {
      "id": 887635,
      "author": "Федор Игнатенко",
      "text": "ЯМЫВАС",
      "date": "2026-02-20T06:48:52+00:00"
    },
    {
      "id": 887624,
      "author": "Airat M",
      "text": "Цой жив!",
      "date": "2026-02-20T06:40:02+00:00"
    },
    {
      "id": 887622,
      "author": "Адвокат Андрей Белов",
      "text": "Должно же было что-то на замену «Гражданам СССР» прийти",
      "date": "2026-02-20T06:27:41+00:00"
    },
    {
      "id": 887621,
      "author": "Andrey Chevychelov",
      "text": "ВАС жил, ВАС жив, ВАС будет жить",
      "date": "2026-02-20T06:26:13+00:00"
    },
    {
      "id": 887620,
      "author": "Александр Малютин",
      "text": "Думаю, что на Гарант нахлынул ИИ, который похоже уже даёт имена документам)",
      "date": "2026-02-20T06:25:48+00:00"
    },
    {
      "id": 887619,
      "author": "Сергей Пивко",
      "text": "В Консультанте опечатки нет\nВидимо, это на Гарант ностальгия нахлынула",
      "date": "2026-02-20T06:25:00+00:00"
    },
    {
      "id": 887618,
      "author": "Дмитрий",
      "text": "В Консультанте плюс нет таких описок. Жаль)",
      "date": "2026-02-20T06:24:49+00:00"
    },
    {
      "id": 887617,
      "author": "Ульяна",
      "text": "Ожил и начал рассматривать уголовные дела 😂",
      "date": "2026-02-20T06:24:39+00:00"
    },
    {
      "id": 887616,
      "author": "Александр Латыев",
      "text": "жив и занимается уголовными делами! Правда, в несколько странном составе",
      "date": "2026-02-20T06:24:30+00:00"
    },
    {
      "id": 887614,
      "author": "RIK",
      "text": "Партизаны Антона Александровича посылают сигнал - \"борьба продолжается\"💁‍♂😄",
      "date": "2026-02-20T06:23:43+00:00"
    },
    {
      "id": 887613,
      "author": "Igor Baiguzov",
      "text": "Жив в наших сердцах и умах навсегда",
      "date": "2026-02-20T06:20:57+00:00"
    },
    {
      "id": 887611,
      "author": "Alim",
      "text": "Ладно, теперь мне станет не так стыдно за опечатки в документах",
      "date": "2026-02-20T06:16:22+00:00"
    },
    {
      "id": 887610,
      "author": "Alexey Alexey",
      "text": "нужен ВАС РФ в изгнании как временная мера",
      "date": "2026-02-20T06:16:20+00:00"
    },
    {
      "id": 887604,
      "author": "Карабас Барабас",
      "text": "Чудом спасшийся суд был укрыт верными боярами из управления частного права и пошел скитаться в народ под именем старца Романа Сергеевича",
      "date": "2026-02-20T06:13:07+00:00"
    },
    {
      "id": 887603,
      "author": "Law For You",
      "text": "Как Витя Цой, только ВАС.",
      "date": "2026-02-20T06:12:54+00:00"
    },
    {
      "id": 887602,
      "author": "Максим Щербаков",
      "text": "Подпольный ВАС)",
      "date": "2026-02-20T06:11:29+00:00"
    },
    {
      "id": 887600,
      "author": "Максим",
      "text": "Мы чего-то не знаем?)))",
      "date": "2026-02-20T06:06:23+00:00"
    },
    {
      "id": 887599,
      "author": "Aw",
      "text": "Как обычно - читайте мелкий шрифт",
      "date": "2026-02-20T06:06:16+00:00"
    },
    {
      "id": 887598,
      "author": "A",
      "text": "И пошёл шёпот по толпе: ВАС жив... ВАС жив... А потом громко: ВАС ЖИВ! и все упали на колени",
      "date": "2026-02-20T06:05:57+00:00"
    },
    {
      "id": 887597,
      "author": "Карабас Барабас",
      "text": "Иногда они возвращаются...",
      "date": "2026-02-20T06:04:50+00:00"
    },
    {
      "id": 887596,
      "author": null,
      "text": "Только не списывай точь в точь",
      "date": "2026-02-20T06:04:45+00:00"
    }
  ]
}